cuvette/aliases.py
cuvette/gui.py
cuvette/launcher.py
cuvette/session.py
cuvette/constants/clusters.py
cuvette/constants/quotes.py
cuvette/constants/secrets.py
cuvette/figlet/__init__.py
cuvette/figlet/figlet.py
cuvette/figlet/fonts/rozzo.flf
cuvette/figlet/fonts/standard.flf
cuvette/scripts/change_priority.py
cuvette/scripts/get_free_gpus.py
cuvette/scripts/get_jobs.py
cuvette/scripts/get_results.py
cuvette/scripts/list_hosts.py
cuvette/scripts/manage_workspace.py
cuvette/scripts/parse_logs.py
cuvette/scripts/restart_jobs.py
cuvette/scripts/stop_jobs.py
cuvette/scripts/stream_logs.py
cuvette/scripts/update_port.py
cuvette/utils/general.py
cuvette/utils/poormansbeaker.py
cuvette/utils/subproccesses.py
cuvette/widget/main.py
cuvette-0.3.5.dist-info/METADATA
cuvette-0.3.5.dist-info/WHEEL
cuvette-0.3.5.dist-info/entry_points.txt
cuvette-0.3.5.dist-info/top_level.txt
cuvette-0.3.5.dist-info/RECORD
