Metadata-Version: 2.4
Name: cuvette
Version: 0.3.5
Requires-Python: >=3.10
Requires-Dist: beaker-py>=2.0.1
Requires-Dist: rich
Requires-Dist: deviousutils
Provides-Extra: widget
Requires-Dist: rumps; extra == "widget"
Requires-Dist: py2app; extra == "widget"
Provides-Extra: openai
Requires-Dist: openai; extra == "openai"
Provides-Extra: dev
Requires-Dist: ruff; extra == "dev"
Requires-Dist: mypy<1.4,>=1.0; extra == "dev"
Requires-Dist: black<24.0,>=23.1; extra == "dev"
Requires-Dist: isort<5.14,>=5.12; extra == "dev"
Requires-Dist: build; extra == "dev"
Requires-Dist: twine>=1.11.0; extra == "dev"
Provides-Extra: all
Requires-Dist: cuvette[dev,openai,widget]; extra == "all"
